bmiTestmoudul/bmiTestmoudul1.py
bmiTestmoudul-0.0.0.1.dist-info/METADATA
bmiTestmoudul-0.0.0.1.dist-info/WHEEL
bmiTestmoudul-0.0.0.1.dist-info/top_level.txt
bmiTestmoudul-0.0.0.1.dist-info/RECORD
